setup.py
src/googleanalytics/__init__.py
src/googleanalytics/account.py
src/googleanalytics/config.py
src/googleanalytics/connection.py
src/googleanalytics/data.py
src/googleanalytics/exception.py
src/googleanalytics/tests.py
src/python_googleanalytics.egg-info/PKG-INFO
src/python_googleanalytics.egg-info/SOURCES.txt
src/python_googleanalytics.egg-info/dependency_links.txt
src/python_googleanalytics.egg-info/requires.txt
src/python_googleanalytics.egg-info/top_level.txt