Metadata-Version: 1.0
Name: python-googleanalytics
Version: 1.0
Summary: A python library for talking to the Google Analytics API
Home-page: http://github.com/clintecker/python-googleanalytics
Author: Clint Ecker
Author-email: me@clintecker.com
License: BSD
Platform: UNKNOWN
Classifier: Development Status :: 4 - Beta
Classifier: Intended Audience :: Developers
Classifier: License :: OSI Approved :: BSD License
Classifier: Operating System :: OS Independent
Classifier: Programming Language :: Python
Classifier: Topic :: Internet
